cltpj/__init__.py
cltpj/__main__.py
cltpj/clt.py
cltpj/constantes.py
cltpj/impostos.py
cltpj/optimiza.py
cltpj/pj_simples.py
cltpj-0.2.1.dist-info/license.txt
cltpj-0.2.1.dist-info/METADATA
cltpj-0.2.1.dist-info/WHEEL
cltpj-0.2.1.dist-info/RECORD
