Metadata-Version: 2.1
Name: cltpj
Version: 0.2.1
Summary: Cálculo aproximado de salário líquido CLT x PJ
License: GNU GPL v3
Author: Nilo Menezes
Author-email: nilo@nilo.pro.br
Requires-Python: >=3.12,<4.0
Classifier: Development Status :: 4 - Beta
Classifier: Environment :: Console
Classifier: Intended Audience :: End Users/Desktop
Classifier: License :: OSI Approved :: GNU General Public License v3 (GPLv3)
Classifier: License :: Other/Proprietary License
Classifier: Natural Language :: Portuguese (Brazilian)
Classifier: Programming Language :: Python :: 3
Classifier: Programming Language :: Python :: 3.12
Requires-Dist: rich (>=13.7.1,<14.0.0)
Requires-Dist: scipy (>=1.14.0,<2.0.0)
